{"chapter":1,"bookCode":"1timothy","size":20,"bookName":"1 Timothy","bookNameJPN":"テモテへの手紙Ⅰ","verses":{"1":"私たちの救い主なる神と私たちの望みなるキリスト・イエスとの命令による、キリスト・イエスの使徒パウロから、","2":"信仰による真実のわが子テモテへ。父なる神と私たちの主なるキリスト・イエスから、恵みとあわれみと平安とがありますように。","3":"私がマケドニヤに出発するとき、あなたにお願いしたように、あなたは、エペソにずっととどまっていて、ある人たちが違った教えを説いたり、","4":"果てしのない空想話と系図とに心を奪われたりしないように命じてください。そのようなものは、論議を引き起こすだけで、信仰による神の救いのご計画の実現をもたらすものではありません。","5":"この命令は、きよい心と正しい良心と偽りのない信仰とから出て来る愛を、目標としています。","6":"ある人たちはこの目当てを見失い、わき道にそれて無益な議論に走り、","7":"律法の教師でありたいと望みながら、自分の言っていることも、また強く主張していることについても理解していません。","8":"しかし私たちは知っています。律法は、もし次のことを知っていて正しく用いるならば、良いものです。","9":"すなわち、律法は、正しい人のためにあるのではなく、律法を無視する不従順な者、不敬虔な罪人、汚らわしい俗物、父や母を殺す者、人を殺す者、","10":"不品行な者、男色をする者、人を誘拐する者、うそをつく者、偽証をする者などのため、またそのほか健全な教えにそむく事のためにあるのです。","11":"祝福に満ちた神の、栄光の福音によれば、こうなのであって、私はその福音をゆだねられたのです。","12":"私は、私を強くしてくださる私たちの主キリスト・イエスに感謝をささげています。なぜなら、キリストは、私をこの務めに任命して、私を忠実な者と認めてくださったからです。","13":"私は以前は、神をけがす者、迫害する者、暴力をふるう者でした。それでも、信じていないときに知らないでしたことなので、あわれみを受けたのです。","14":"私たちの主の、この恵みは、キリスト・イエスにある信仰と愛とともに、ますます満ちあふれるようになりました。","15":"「キリスト・イエスは、罪人を救うためにこの世に来られた。」ということばは、まことであり、そのまま受け入れるに値するものです。私はその罪人のかしらです。","16":"しかし、そのような私があわれみを受けたのは、イエス・キリストが、今後彼を信じて永遠のいのちを得ようとしている人々の見本にしようと、まず私に対してこの上ない寛容を示してくださったからです。","17":"どうか、世々の王、すなわち、滅びることなく、目に見えない唯一の神に、誉れと栄えとが世々限りなくありますように。アーメン。","18":"私の子テモテよ。以前あなたについてなされた預言に従って、私はあなたにこの命令をゆだねます。それは、あなたがあの預言によって、信仰と正しい良心を保ち、勇敢に戦い抜くためです。","19":"ある人たちは、正しい良心を捨てて、信仰の破船に会いました。","20":"その中には、ヒメナオとアレキサンデルがいます。私は、彼らをサタンに引き渡しました。それは、神をけがしてはならないことを、彼らに学ばせるためです。"}}