{"chapter":19,"bookCode":"2chronicles","size":11,"bookName":"2 Chronicles","bookNameJPN":"歴代誌Ⅱ","verses":{"1":"ユダの王ヨシャパテは無事に自分の家に帰り、エルサレムに戻った。","2":"すると、先見者ハナニの子エフーが彼の前に出向いて来て、ヨシャパテ王に言った。「悪者を助けるべきでしょうか。あなたは主を憎む者たちを愛してよいのでしょうか。これによって、あなたの上に、主の前から怒りが下ります。","3":"しかし、あなたには、良いことも幾つか見られます。あなたはこの地からアシェラ像を除き去り、心を定めて常に神を求めて来られました。」","4":"ヨシャパテはエルサレムに住んだ。それから、彼はもう一度ベエル・シェバからエフライムの山地に至る民の中へ出て行き、彼らをその父祖の神、主に立ち返らせた。","5":"さらに、彼はこの地、すなわち、ユダにあるすべての城壁のある町々にさばきつかさを立て、町ごとにこれを任命し、","6":"さばきつかさたちにこう言った。「あなたがたは自分のする事に注意しなさい。あなたがたがさばくのは、人のためではなく、主のためだからです。この方は、さばきが行なわれるとき、あなたがたとともにおられるのです。","7":"今、主への恐れがあなたがたにあるように。忠実に行ないなさい。私たちの神、主には、不正も、えこひいきも、わいろを取ることもないからです。」","8":"なお、ヨシャパテはエルサレムでは、レビ人と祭司の中から、またイスラエルに属する一族のかしらたちの中から、主のさばき、および訴訟に携わる者たちを任命していた。エルサレムに帰ったとき、","9":"彼はこの人々に次のように命じた。「あなたがたは、主を恐れ、忠実に、また全き心をもって、このように行なわなければなりません。","10":"おのおのの町に住んでいるあなたがたの兄弟たちから、あるいは互いの流血事件について、あるいは律法、命令、おきて、定めなどについて、あなたがたのところに訴訟が持ち込まれた場合には、いつでも、あなたがたは、彼らが主に対して罪を負い、その結果、あなたがたとあなたがたの兄弟たちの上に御怒りが下ることのないよう、彼らに警告を与えなければなりません。あなたがたはこのように行ないなさい。そうすれば罪を負わずに済むのです。","11":"ご覧なさい。あなたがたの上のかしら、祭司アマルヤは、主の事がら全体に当たります。また、ユダの家のつかさイシュマエルの子ゼバデヤは王の事がら全体に当たってくれます。さらに、あなたがたの前のレビ人はつかさです。勇気を出して実行しなさい。主が善人とともにいてくださるように。」"}}