{"chapter":1,"bookCode":"galatians","size":24,"bookName":"Galatians","bookNameJPN":"ガラテヤ人への手紙","verses":{"1":"使徒となったパウロ\u2014\u2014私が使徒となったのは、人間から出たことでなく、また人間の手を通したことでもなく、イエス・キリストと、キリストを死者の中からよみがえらせた父なる神によったのです。\u2014\u2014","2":"および私とともにいるすべての兄弟たちから、ガラテヤの諸教会へ。","3":"どうか、私たちの父なる神と主イエス・キリストから、恵みと平安があなたがたの上にありますように。","4":"キリストは、今の悪の世界から私たちを救い出そうとして、私たちの罪のためにご自身をお捨てになりました。私たちの神であり父である方のみこころによったのです。","5":"どうか、この神に栄光がとこしえにありますように。アーメン。","6":"私は、キリストの恵みをもってあなたがたを召してくださったその方を、あなたがたがそんなにも急に見捨てて、ほかの福音に移って行くのに驚いています。","7":"ほかの福音といっても、もう一つ別に福音があるのではありません。あなたがたをかき乱す者たちがいて、キリストの福音を変えてしまおうとしているだけです。","8":"しかし、私たちであろうと、天の御使いであろうと、もし私たちが宣べ伝えた福音に反することをあなたがたに宣べ伝えるなら、その者はのろわれるべきです。","9":"私たちが前に言ったように、今もう一度私は言います。もしだれかが、あなたがたの受けた福音に反することを、あなたがたに宣べ伝えているなら、その者はのろわれるべきです。","10":"いま私は人に取り入ろうとしているのでしょうか。いや。神に、でしょう。あるいはまた、人の歓心を買おうと努めているのでしょうか。もし私がいまなお人の歓心を買おうとするようなら、私はキリストのしもべとは言えません。","11":"兄弟たちよ。私はあなたがたに知らせましょう。私が宣べ伝えた福音は、人間によるものではありません。","12":"私はそれを人間からは受けなかったし、また教えられもしませんでした。ただイエス・キリストの啓示によって受けたのです。","13":"以前ユダヤ教徒であったころの私の行動は、あなたがたがすでに聞いているところです。私は激しく神の教会を迫害し、これを滅ぼそうとしました。","14":"また私は、自分と同族で同年輩の多くの者たちに比べ、はるかにユダヤ教に進んでおり、先祖からの伝承に人一倍熱心でした。","15":"けれども、生まれたときから私を選び分け、恵みをもって召してくださった方が、","16":"異邦人の間に御子を宣べ伝えさせるために、御子を私のうちに啓示することをよしとされたとき、私はすぐに、人には相談せず、","17":"先輩の使徒たちに会うためにエルサレムにも上らず、アラビヤに出て行き、またダマスコに戻りました。","18":"それから三年後に、私はケパをたずねてエルサレムに上り、彼のもとに十五日間滞在しました。","19":"しかし、主の兄弟ヤコブは別として、ほかの使徒にはだれにも会いませんでした。","20":"私があなたがたに書いていることには、神の御前で申しますが、偽りはありません。","21":"それから、私はシリヤおよびキリキヤの地方に行きました。","22":"しかし、キリストにあるユダヤの諸教会には顔を知られていませんでした。","23":"けれども、「以前私たちを迫害した者が、そのとき滅ぼそうとした信仰を今は宣べ伝えている。」と聞いてだけはいたので、","24":"彼らは私のことで神をあがめていました。"}}