{"chapter":28,"bookCode":"ezekiel","size":26,"bookName":"Ezekiel","bookNameJPN":"エゼキエル書","verses":{"1":"次のような主のことばが私にあった。","2":"「人の子よ。ツロの君主に言え。神である主はこう仰せられる。あなたは心高ぶり、『私は神だ。海の真中で神の座に着いている。』と言った。あなたは自分の心を神のようにみなしたが、あなたは人であって、神ではない。","3":"あなたはダニエルよりも知恵があり、どんな秘密もあなたに隠されていない。","4":"あなたは自分の知恵と英知によって財宝を積み、金や銀を宝物倉にたくわえた。","5":"商いに多くの知恵を使って財宝をふやし、あなたの心は、財宝で高ぶった。","6":"それゆえ、神である主はこう仰せられる。あなたは自分の心を神の心のようにみなした。","7":"それゆえ、他国人、最も横暴な異邦の民を連れて来て、あなたを攻めさせる。彼らはあなたの美しい知恵に向かって剣を抜き、あなたの輝きを汚し、","8":"あなたを穴に投げ入れる。あなたは海の真中で、刺し殺される者の死を遂げる。","9":"それでもあなたは、自分を殺す者の前で、『私は神だ。』と言うのか。あなたは人であって、神ではない。あなたはあなたを刺し殺す者たちの手の中にある。","10":"あなたは異邦人の手によって割礼を受けていない者の死を遂げる。わたしがこれを語ったからだ。\u2014\u2014神である主の御告げ。\u2014\u2014」","11":"次のような主のことばが私にあった。","12":"「人の子よ。ツロの王について哀歌を唱えて、彼に言え。神である主はこう仰せられる。あなたは全きものの典型であった。知恵に満ち、美の極みであった。","13":"あなたは神の園、エデンにいて、あらゆる宝石があなたをおおっていた。赤めのう、トパーズ、ダイヤモンド、緑柱石、しまめのう、碧玉、サファイヤ、トルコ玉、エメラルド。あなたのタンバリンと笛とは金で作られ、これらはあなたが造られた日に整えられていた。","14":"わたしはあなたを油そそがれた守護者ケルブとともに、神の聖なる山に置いた。あなたは火の石の間を歩いていた。","15":"あなたの行ないは、あなたが造られた日からあなたに不正が見いだされるまでは、完全だった。","16":"あなたの商いが繁盛すると、あなたのうちに暴虐が満ち、あなたは罪を犯した。そこで、わたしはあなたを汚れたものとして神の山から追い出し、守護者ケルブが火の石の間からあなたを消えうせさせた。","17":"あなたの心は自分の美しさに高ぶり、その輝きのために自分の知恵を腐らせた。そこで、わたしはあなたを地に投げ出し、王たちの前に見せものとした。","18":"あなたは不正な商いで不義を重ね、あなたの聖所を汚した。わたしはあなたのうちから火を出し、あなたを焼き尽くした。こうして、すべての者が見ている前で、わたしはあなたを地上の灰とした。","19":"国々の民のうちであなたを知る者はみな、あなたのことでおののいた。あなたは恐怖となり、とこしえになくなってしまう。」","20":"次のような主のことばが私にあった。","21":"「人の子よ。顔をシドンに向け、それに預言して、","22":"言え。神である主はこう仰せられる。シドンよ。わたしはおまえに立ち向かい、おまえのうちでわたしの栄光を現わす。わたしがシドンにさばきを下し、わたしの聖なることをそこに示すとき、彼らは、わたしが主であることを知ろう。","23":"わたしはそこに疫病を送り込む。そのちまたには血が流れ、四方から攻める剣のため、刺し殺された者がその中に倒れる。このとき、彼らはわたしが主であることを知ろう。","24":"イスラエルの家にとって、突き刺すいばらも、その回りから彼らに痛みを与え、侮るとげもなくなるとき、彼らは、わたしが神、主であることを知ろう。","25":"神である主はこう仰せられる。わたしがイスラエルの家を、散らされていた国々の民の中から集めるとき、わたしは諸国の民の目のまえで、わたしの聖なることを示そう。彼らは、わたしがわたしのしもべヤコブに与えた土地に住みつこう。","26":"彼らはそこに安らかに住み、家々を建て、ぶどう畑を作る。彼らは安らかにそこに住みつこう。回りで彼らを侮るすべての者にわたしがさばきを下すとき、彼らは、わたしが彼らの神、主であることを知ろう。」"}}