{"chapter":30,"bookCode":"ezekiel","size":26,"bookName":"Ezekiel","bookNameJPN":"エゼキエル書","verses":{"1":"次のような主のことばが私にあった。","2":"「人の子よ。預言して言え。神である主はこう仰せられる。泣きわめけ。ああ、その日よ。","3":"その日は近い。主の日は近い。その日は曇った日、諸国の民の終わりの時だ。","4":"剣がエジプトに下り、刺し殺される者がエジプトで倒れ、その富は奪われ、その基がくつがえされるとき、クシュには苦痛が起きる。","5":"クシュ、プテ、ルデ、アラビヤ全体、クブ、彼らの同盟国の人々も、彼らとともに剣に倒れる。","6":"主はこう仰せられる。エジプトをささえる者は倒れ、その力強い誇りは見下げられ、ミグドルからセベネに至るまでみな剣に倒れる。\u2014\u2014神である主の御告げ。\u2014\u2014","7":"エジプトは荒れ果てた国々の間で荒れ果て、その町々も、廃墟となった町々の間にあって荒れ果てる。","8":"わたしがエジプトに火をつけ、これを助ける者たちがみな滅ぼされるとき、彼らは、わたしが主であることを知ろう。","9":"その日、わたしのもとから使者たちが船で送り出され、安心しているクシュ人をおののかせる。エジプトの日に、彼らの間に苦痛が起きる。今、その日が来ている。","10":"神である主はこう仰せられる。わたしはバビロンの王ネブカデレザルによって、エジプトの富を取り除く。","11":"彼と、彼の民、すなわち、最も横暴な異邦の民がその地を滅ぼすために遣わされる。彼らは剣を抜いてエジプトを攻め、その地を刺し殺された者で満たす。","12":"わたしはナイル川を干上がった地とし、その国を悪人どもの手に売り、他国人の手によって、その国とそこにあるすべての物を荒れ果てさせる。主であるわたしがこれを語る。","13":"神である主はこう仰せられる。わたしは偶像を打ちこわし、ノフから偽りの神々を取り除く。エジプトの国には、もう君主が立たなくなる。わたしはエジプトの地に恐怖を与える。","14":"わたしはパテロスを荒らし、ツォアンに火をつけ、ノにさばきを下す。","15":"わたしはエジプトのとりでシンにわたしの憤りを注ぎ、ノの群集を断ち滅ぼす。","16":"わたしはエジプトに火をつける。シンは大いに苦しみ、ノは砕かれ、ノフは昼間、敵に襲われる。","17":"オンとピ・ベセテの若い男たちは剣に倒れ、女たちはとりことなって行く。","18":"わたしがエジプトのくびきを砕き、その力強い誇りが絶やされるとき、タフパヌヘスでは日は暗くなり、雲がそこをおおい、その娘たちはとりことなって行く。","19":"わたしがエジプトにさばきを下すとき、彼らは、わたしが主であることを知ろう。」","20":"第十一年の第一の月の七日、私に次のような主のことばがあった。","21":"「人の子よ。わたしはエジプトの王パロの腕を砕いた。見よ。それは包まれず、手当をされず、ほうたいを当てて包まれず、元気になって剣を取ることもできない。","22":"それゆえ、神である主はこう仰せられる。わたしはエジプトの王パロに立ち向かい、強いが砕かれている彼の腕を砕き、その手から剣を落とさせる。","23":"わたしはエジプト人を諸国の民の中に散らし、国々に追い散らす。","24":"しかし、わたしはバビロンの王の腕を強くし、わたしの剣を彼の手に渡し、パロの腕を砕く。彼は刺された者がうめくようにバビロンの王の前でうめく。","25":"わたしはバビロンの王の腕を強くし、パロの腕を垂れさせる。このとき、わたしがバビロンの王の手にわたしの剣を渡し、彼がそれをエジプトの地に差し向けると、彼らは、わたしが主であることを知ろう。","26":"わたしがエジプト人を諸国の民の中に散らし、彼らを国々に追い散らすとき、彼らは、わたしが主であることを知ろう。」"}}