{"chapter":3,"bookCode":"amos","size":15,"bookName":"Amos","bookNameJPN":"アモス書","verses":{"1":"イスラエルの子らよ。主があなたがた、すなわちわたしがエジプトの地から連れ上ったすべての氏族について言った、このことばを聞け。","2":"わたしは地上のすべての部族の中から、あなたがただけを選び出した。それゆえ、わたしはあなたがたのすべての咎をあなたがたに報いる。","3":"ふたりの者は、仲がよくないのに、いっしょに歩くだろうか。","4":"獅子は、獲物がないのに、森の中でほえるだろうか。若い獅子は、何も捕えないのに、そのほら穴から叫ぶだろうか。","5":"鳥は、わながかけられないのに、地の鳥網にかかるだろうか。鳥網は、何も捕えないのに、地からはね上がるだろうか。","6":"町で角笛が鳴ったら、民は驚かないだろうか。町にわざわいが起これば、それは主が下されるのではないだろうか。","7":"まことに、神である主は、そのはかりごとを、ご自分のしもべ、預言者たちに示さないでは、何事もなさらない。","8":"獅子がほえる。だれが恐れないだろう。神である主が語られる。だれが預言しないでいられよう。","9":"アシュドデの宮殿と、エジプトの地の宮殿に告げて言え。「サマリヤの山々の上に集まり、そのうちの大恐慌と、その中のしいたげを見よ。","10":"彼らは正しいことを行なうことを知らない。\u2014\u2014主の御告げ。\u2014\u2014彼らは自分たちの宮殿で、暴虐と暴行を重ねている。」","11":"それゆえ、神である主はこう仰せられる。「敵だ。この国を取り囲んでいる。彼はあなたの権威を地に落とし、あなたの宮殿はかすめ奪われる。」","12":"主はこう仰せられる。「羊飼いが、雄獅子の口から、二本の足、あるいは耳たぶを取り返すように、サマリヤに住んでいるイスラエルの子らは、寝台の隅やダマスコの長いすから救い出される。」","13":"「聞け。そして、これをヤコブの家に証言せよ。\u2014\u2014神である主、万軍の神の御告げ。\u2014\u2014","14":"まことに、イスラエルがわたしに犯したそむきの罪を、わたしが罰する日に、わたしはベテルの祭壇を罰する。その祭壇の角は折られて、地に落ちる。","15":"わたしは冬の家と夏の家とを打つ。象牙の家々は滅び、多くの家々は消えうせる。\u2014\u2014主の御告げ。\u2014\u2014」"}}