{"chapter":1,"bookCode":"leviticus","size":17,"bookName":"Leviticus","bookNameJPN":"レビ記","verses":{"1":"主はモーセを呼び寄せ、会見の天幕から彼に告げて仰せられた。","2":"「イスラエル人に告げて言え。もし、あなたがたが主にささげ物をささげるときは、だれでも、家畜の中から牛か羊をそのささげ物としてささげなければならない。","3":"もしそのささげ物が、牛の全焼のいけにえであれば、傷のない雄牛をささげなければならない。それを、主に受け入れられるために会見の天幕の入口の所に連れて来なければならない。","4":"その人は、全焼のいけにえの頭の上に手を置く。それが彼を贖うため、彼の代わりに受け入れられるためである。","5":"その人は主の前で、その若い牛をほふり、祭司であるアロンの子らは、その血を持って行って、会見の天幕の入口にある祭壇の回りに、その血を注ぎかけなさい。","6":"また、その全焼のいけにえの皮をはぎ、いけにえを部分に切り分けなさい。","7":"祭司であるアロンの子らは祭壇の上に火を置き、その火の上にたきぎを整えなさい。","8":"祭司であるアロンの子らは、その切り分けた部分と、頭と、脂肪とを祭壇の上にある火の上のたきぎの上に整えなさい。","9":"内臓と足は、その人が水で洗わなければならない。祭司はこれら全部を祭壇の上で全焼のいけにえとして焼いて煙にする。これは、主へのなだめのかおりの火によるささげ物である。","10":"しかし、もし全焼のいけにえのためのささげ物が、羊の群れ、すなわち子羊またはやぎの中からなら、傷のない雄でなければならない。","11":"その人は祭壇の北側で、主の前にこれをほふりなさい。そして祭司であるアロンの子らは、その血を祭壇の回りに注ぎかけなさい。","12":"また、その人はそれを部分に切り分け、祭司はこれを頭と脂肪に添えて祭壇の上にある火の上のたきぎの上に整えなさい。","13":"内臓と足は、その人が水で洗わなければならない。こうして祭司はそれら全部をささげ、祭壇の上で焼いて煙にしなさい。これは全焼のいけにえであり、主へのなだめのかおりの火によるささげ物である。","14":"もしその人の主へのささげ物が、鳥の全焼のいけにえであるなら、山鳩または家鳩のひなの中から、そのささげ物をささげなければならない。","15":"祭司は、それを祭壇のところに持って来て、その頭をひねり裂き、祭壇の上でそれを焼いて煙にしなさい。ただし、その血は祭壇の側面に絞り出す。","16":"またその汚物のはいった餌袋を取り除き、祭壇の東側の灰捨て場に投げ捨てなさい。","17":"さらに、その翼を引き裂きなさい。それを切り離してはならない。そして、祭司はそれを祭壇の上、火の上にあるたきぎの上で焼いて煙にしなさい。これは全焼のいけにえであり、主へのなだめのかおりの火によるささげ物である。"}}